{
  "background_color": "#FFFFFF",
  "has_background_image": true,
  "background_image_description": "Full-canvas, desaturated grayscale office workspace photo: hands writing on documents with charts/graphs, a tablet on the desk, and scattered papers; soft blur and light overlay.",
  "nodes": [
    {
      "type": "image",
      "asset_description": "Large abstract wave shape anchored to the bottom-right corner with a smooth orange gradient transitioning from #FF8A00 to #C65A00.",
      "x": 900,
      "y": 980,
      "width": 700,
      "height": 620,
      "rotation": 0
    },
    {
      "type": "image",
      "asset_description": "Partial solid orange circle clipped by the canvas at the top-left corner (fill #FF8A00).",
      "x": 0,
      "y": 0,
      "width": 170,
      "height": 170,
      "rotation": 0
    },
    {
      "type": "image",
      "asset_description": "Thick circular frame with an orange gradient border (#FF9900 to #D15A00); center cut out for a portrait.",
      "x": 980,
      "y": 600,
      "width": 560,
      "height": 560,
      "rotation": 0
    },
    {
      "type": "image",
      "asset_description": "Cropped circular portrait of a smiling young woman with shoulder-length brown hair on a neutral beige background, wearing a sleeveless light top.",
      "x": 1030,
      "y": 650,
      "width": 460,
      "height": 460,
      "rotation": 0
    },
    {
      "type": "image",
      "asset_description": "Small orange accent circle with a subtle gradient from #FF9A23 to #D46600 overlapping the top-right of the portrait frame.",
      "x": 1400,
      "y": 590,
      "width": 140,
      "height": 140,
      "rotation": 0
    },
    {
      "type": "image",
      "asset_description": "Rounded pill badge (fully rounded corners) filled with a red-to-pink gradient (#FF4D59 to #E0353B).",
      "x": 1120,
      "y": 160,
      "width": 280,
      "height": 80,
      "rotation": 0
    },
    {
      "type": "text",
      "text": "LIVE",
      "x": 160,
      "y": 350,
      "width": 520,
      "height": 180,
      "rotation": 0,
      "font-family": "Anton",
      "font-size": 150,
      "color": "#0B3C46",
      "text-align": "left",
      "font-weight": "900",
      "font-style": "normal",
      "text-decoration": "none",
      "text-transform": "uppercase"
    },
    {
      "type": "text",
      "text": "WEBINAR",
      "x": 160,
      "y": 510,
      "width": 840,
      "height": 230,
      "rotation": 0,
      "font-family": "Anton",
      "font-size": 220,
      "color": "#0B3C46",
      "text-align": "left",
      "font-weight": "900",
      "font-style": "normal",
      "text-decoration": "none",
      "text-transform": "uppercase"
    },
    {
      "type": "text",
      "text": "The Best Solution For Growing Your Business",
      "x": 160,
      "y": 700,
      "width": 720,
      "height": 54,
      "rotation": 0,
      "font-family": "Montserrat",
      "font-size": 32,
      "color": "#4A4A4A",
      "text-align": "left",
      "font-weight": "400",
      "font-style": "normal",
      "text-decoration": "none",
      "text-transform": "none"
    },
    {
      "type": "text",
      "text": "FRIDAY",
      "x": 160,
      "y": 790,
      "width": 360,
      "height": 70,
      "rotation": 0,
      "font-family": "Montserrat",
      "font-size": 60,
      "color": "#F57C00",
      "text-align": "left",
      "font-weight": "800",
      "font-style": "normal",
      "text-decoration": "none",
      "text-transform": "uppercase"
    },
    {
      "type": "text",
      "text": "08 JUNE 2025",
      "x": 160,
      "y": 870,
      "width": 520,
      "height": 90,
      "rotation": 0,
      "font-family": "Montserrat",
      "font-size": 80,
      "color": "#F57C00",
      "text-align": "left",
      "font-weight": "800",
      "font-style": "normal",
      "text-decoration": "none",
      "text-transform": "uppercase"
    },
    {
      "type": "text",
      "text": "8.00 PM",
      "x": 160,
      "y": 960,
      "width": 320,
      "height": 70,
      "rotation": 0,
      "font-family": "Montserrat",
      "font-size": 60,
      "color": "#F57C00",
      "text-align": "left",
      "font-weight": "800",
      "font-style": "normal",
      "text-decoration": "none",
      "text-transform": "uppercase"
    },
    {
      "type": "image",
      "asset_description": "Circular phone icon: white filled circle with a dark teal ring stroke (#0B3C46) and a handset glyph in the same teal.",
      "x": 150,
      "y": 1228,
      "width": 72,
      "height": 72,
      "rotation": 0
    },
    {
      "type": "text",
      "text": "+1234 5678 910",
      "x": 240,
      "y": 1240,
      "width": 520,
      "height": 56,
      "rotation": 0,
      "font-family": "Montserrat",
      "font-size": 46,
      "color": "#0B3C46",
      "text-align": "left",
      "font-weight": "800",
      "font-style": "normal",
      "text-decoration": "none",
      "text-transform": "none"
    },
    {
      "type": "text",
      "text": "LIVE STREAMING",
      "x": 1120,
      "y": 180,
      "width": 280,
      "height": 44,
      "rotation": 0,
      "font-family": "Montserrat",
      "font-size": 32,
      "color": "#FFFFFF",
      "text-align": "center",
      "font-weight": "700",
      "font-style": "normal",
      "text-decoration": "none",
      "text-transform": "uppercase"
    },
    {
      "type": "text",
      "text": "ROSSA SMITH (GRAPHIC DESIGN)",
      "x": 1000,
      "y": 1360,
      "width": 560,
      "height": 56,
      "rotation": 0,
      "font-family": "Montserrat",
      "font-size": 38,
      "color": "#FFFFFF",
      "text-align": "center",
      "font-weight": "600",
      "font-style": "normal",
      "text-decoration": "none",
      "text-transform": "uppercase"
    }
  ],
  "canvas_width": 1600,
  "canvas_height": 1600
}